NN4MSP/__init__.py
NN4MSP/dataset.py
NN4MSP/functions.py
NN4MSP/data/HVAC_data.csv
NN4MSP-2.28.dist-info/LICENSE.md
NN4MSP-2.28.dist-info/METADATA
NN4MSP-2.28.dist-info/WHEEL
NN4MSP-2.28.dist-info/top_level.txt
NN4MSP-2.28.dist-info/RECORD
